air_cli/__init__.py
air_cli/__main__.py
air_cli/air_cli.py
air_cli/cli.py
air_cli/generator.py
air_cli/plugins/markdown_plugin.py
air_cli-0.2.0.dist-info/licenses/LICENSE
air_cli-0.2.0.dist-info/METADATA
air_cli-0.2.0.dist-info/WHEEL
air_cli-0.2.0.dist-info/entry_points.txt
air_cli-0.2.0.dist-info/top_level.txt
air_cli-0.2.0.dist-info/RECORD
